README.md
setup.py
esports_cog_utils/__init__.py
esports_cog_utils/task_runner.py
esports_cog_utils/utils.py
esports_cog_utils.egg-info/PKG-INFO
esports_cog_utils.egg-info/SOURCES.txt
esports_cog_utils.egg-info/dependency_links.txt
esports_cog_utils.egg-info/requires.txt
esports_cog_utils.egg-info/top_level.txt
esports_cog_utils/bayes/__init__.py
esports_cog_utils/bayes/aio_client.py
esports_cog_utils/bayes/client.py
esports_cog_utils/bayes/errors.py
esports_cog_utils/bayes/static_types.py