Metadata-Version: 2.1
Name: esports-cog-utils
Version: 0.1.3
Summary: River's Red cog tools
Home-page: https://github.com/RheingoldRiver/esports_cog_utils
Author: RheingoldRiver
Author-email: river.esports@gmail.com
License: UNKNOWN
Platform: UNKNOWN
Requires-Python: >=3.6
